diligence_service_client/__init__.py
diligence_service_client/api/__init__.py
diligence_service_client/api/due_diligences/__init__.py
diligence_service_client/api/due_diligences/get_due_diligence.py
diligence_service_client/api/projects/__init__.py
diligence_service_client/api/projects/get_project.py
diligence_service_client/client.py
diligence_service_client/errors.py
diligence_service_client/models/__init__.py
diligence_service_client/models/due_diligence.py
diligence_service_client/models/http_validation_error.py
diligence_service_client/models/project.py
diligence_service_client/models/validation_error.py
diligence_service_client/py.typed
diligence_service_client/types.py
diligence_service_client-1.0.4.dist-info/METADATA
diligence_service_client-1.0.4.dist-info/WHEEL
diligence_service_client-1.0.4.dist-info/RECORD
